{
    "54.206.0.6": {
        "server_id": "442",
        "location": "Sydney",
        "flag": "au",
        "hostname": "q3df.run | Sydney",
        "thumbnail": "https://www.holidaysplease.co.uk/assets/images/119-17-sydney%20opera%20house.jpg-BasicCrop-size-500x500.jpg",
        "status": "Stopped",
        "message_id": 962918992081743912,
        "activator": "",
        "activator_dc": "",
        "instance_id": "i-0bf0593216ec334f4",
        "region": "ap-southeast-2",
        "inactivity_count": 0,
        "inactivity_counter": 0
    },
    "3.10.114.224": {
        "server_id": "435",
        "location": "London",
        "flag": "gb",
        "hostname": "q3df.run | London",
        "thumbnail": "http://zimngoma.com/wp-content/uploads/2015/03/london-500x500.jpg",
        "status": "Stopped",
        "message_id": 962918994724143164,
        "activator": "",
        "activator_dc": "",
        "instance_id": "i-01092b4e29b5b4b44",
        "region": "eu-west-2",
        "inactivity_count": 0,
        "inactivity_counter": 0
    },
    "13.51.137.1": {
        "server_id": "436",
        "location": "Stockholm",
        "flag": "se",
        "hostname": "q3df.run | Stockholm",
        "thumbnail": "https://strawberrytours.com/wp-content/uploads/2019/07/Stockholm-500x500.jpg",
        "status": "Stopped",
        "message_id": 962918999715356703,
        "activator": "",
        "activator_dc": "",
        "instance_id": "i-0b90183227214702a",
        "region": "eu-north-1",
        "inactivity_count": 0,
        "inactivity_counter": 0
    },
    "13.245.107.109": {
        "server_id": "431",
        "location": "Cape Town",
        "flag": "za",
        "hostname": "q3df.run | Cape Town",
        "thumbnail": "https://image.arrivalguides.com/500x500/18/f3b9c07583a62553bae420f6d9f1514e.jpg",
        "status": "Stopped",
        "message_id": 962919017155264532,
        "activator": "",
        "activator_dc": "",
        "instance_id": "i-0fd1a077cda2f9a93",
        "region": "af-south-1",
        "inactivity_count": 0,
        "inactivity_counter": 0
    },
    "54.94.102.4": {
        "server_id": "427",
        "location": "Sao Paolo",
        "flag": "br",
        "hostname": "q3df.run | Sao Paolo",
        "thumbnail": "https://strawberrytours.com/wp-content/uploads/2019/10/Sao_Paulo_500x500.jpg",
        "status": "Stopped",
        "message_id": 962919019759951872,
        "activator": "",
        "activator_dc": "",
        "instance_id": "i-0396e821c7cfed171",
        "region": "sa-east-1",
        "inactivity_count": 0,
        "inactivity_counter": 0
    }
}